pen2png/__init__.py
pen2png/cli.py
pen2png/process.py
pen2png-0.2.0.dist-info/METADATA
pen2png-0.2.0.dist-info/WHEEL
pen2png-0.2.0.dist-info/entry_points.txt
pen2png-0.2.0.dist-info/top_level.txt
pen2png-0.2.0.dist-info/RECORD
