Metadata-Version: 2.1
Name: pen2png
Version: 0.2.0
Summary: A tool to convert pen drawings to transparent PNGs.
Home-page: https://github.com/hentity/pen2png
Author: Henry Hamer
Author-email: hhame4@gmail.com
License: MIT
Classifier: Programming Language :: Python :: 3
Classifier: License :: OSI Approved :: MIT License
Classifier: Operating System :: OS Independent
Requires-Python: >=3.7
Requires-Dist: numpy
Requires-Dist: opencv-python
Requires-Dist: Pillow
Requires-Dist: pillow-heif
